MANIFEST.in
README.rst
TITLE.txt
lh-agpl3-LICENSE.txt
setup.py
unisos2/__init__.py
unisos2.icm.egg-info/PKG-INFO
unisos2.icm.egg-info/SOURCES.txt
unisos2.icm.egg-info/dependency_links.txt
unisos2.icm.egg-info/namespace_packages.txt
unisos2.icm.egg-info/not-zip-safe
unisos2.icm.egg-info/requires.txt
unisos2.icm.egg-info/top_level.txt
unisos2/icm/__init__.py
unisos2/icm/icm.py